[
  {
    "id": "dc-data-scientist",
    "name": "Deep Learning Essentials",
    "issuer": "Blue Courses",
    "dateObtained": "2025-03",
    "credentialUrl": "https://www.bluecourses.com/certificates/61d81e6d324640549afd9c5f1789b05c",
    "badgeUrl": null
  },
  {
    "id": "dc-python-programmer",
    "name": "[PCEP-30-02] PCEP™ – Certified Entry-Level Python Programmer",
    "issuer": "Python Developer",
    "dateObtained": "2025-01",
    "credentialUrl": "https://www.credly.com/badges/abbdce56-83ca-4f20-a696-869aef4f165e/public_url",
    "badgeUrl": null
  },
  {
    "id": "dc-sql-fundamentals",
    "name": "Tableau Desktop Specialist",
    "issuer": "Tableau",
    "dateObtained": "2024-12",
    "credentialUrl": "https://www.credly.com/badges/307944d0-f6b3-40d2-9f4c-200496bb6b2d/public_url",
    "badgeUrl": null
  }
]